<?xml version="1.0" encoding="utf-8" ?>
<dwsync>
<file name="columns.html" server="C:/wamp64/www/" local="131473765546036010" remote="131473765540000000" Dst="1" />
<file name="complete-callback.html" server="C:/wamp64/www/" local="131473765549043586" remote="131473765540000000" Dst="1" />
<file name="fill-both.html" server="C:/wamp64/www/" local="131473765551583464" remote="131473765550000000" Dst="1" />
<file name="fill-horizontal.html" server="C:/wamp64/www/" local="131473765554214415" remote="131473765550000000" Dst="1" />
<file name="index.html" server="C:/wamp64/www/" local="131473765537864518" remote="131473765530000000" Dst="1" />
<file name="scrolling.html" server="C:/wamp64/www/" local="131473765557220428" remote="131473765550000000" Dst="1" />
<file name="simple.html" server="C:/wamp64/www/" local="131473765559916671" remote="131473765550000000" Dst="1" />
<file name="step-callback.html" server="C:/wamp64/www/" local="131473765562769107" remote="131473765560000000" Dst="1" />
<file name="columns.html" server="C:/wamp64/www/emobi/" local="131835888955985411" remote="131835852950000000" Dst="2" />
<file name="complete-callback.html" server="C:/wamp64/www/emobi/" local="131835888956882301" remote="131835852950000000" Dst="2" />
<file name="fill-both.html" server="C:/wamp64/www/emobi/" local="131835888957850963" remote="131835852950000000" Dst="2" />
<file name="fill-horizontal.html" server="C:/wamp64/www/emobi/" local="131835888958569034" remote="131835852950000000" Dst="2" />
<file name="index.html" server="C:/wamp64/www/emobi/" local="131835888951977512" remote="131835852950000000" Dst="2" />
<file name="scrolling.html" server="C:/wamp64/www/emobi/" local="131835888959415129" remote="131835852950000000" Dst="2" />
<file name="simple.html" server="C:/wamp64/www/emobi/" local="131835888960432432" remote="131835852960000000" Dst="2" />
<file name="step-callback.html" server="C:/wamp64/www/emobi/" local="131835888961699014" remote="131835852960000000" Dst="2" />
</dwsync>