<?xml version="1.0" encoding="utf-8" ?>
<dwsync>
<file name="dataTables.bootstrap.css" server="C:/wamp64/www/" local="131352702710000000" remote="131352702710000000" Dst="1" />
<file name="dataTables.bootstrap.min.css" server="C:/wamp64/www/" local="131352702710000000" remote="131352702710000000" Dst="1" />
<file name="dataTables.foundation.css" server="C:/wamp64/www/" local="131352702710000000" remote="131352702710000000" Dst="1" />
<file name="dataTables.foundation.min.css" server="C:/wamp64/www/" local="131352702710000000" remote="131352702710000000" Dst="1" />
<file name="dataTables.jqueryui.css" server="C:/wamp64/www/" local="131352702710000000" remote="131352702710000000" Dst="1" />
<file name="dataTables.jqueryui.min.css" server="C:/wamp64/www/" local="131352702710000000" remote="131352702710000000" Dst="1" />
<file name="jquery.dataTables.css" server="C:/wamp64/www/" local="131352702710000000" remote="131352702710000000" Dst="1" />
<file name="jquery.dataTables.min.css" server="C:/wamp64/www/" local="131352702710000000" remote="131352702710000000" Dst="1" />
<file name="jquery.dataTables_themeroller.css" server="C:/wamp64/www/" local="131352702710000000" remote="131352702710000000" Dst="1" />
<file name="dataTables.bootstrap.css" server="C:/wamp64/www/emobi/" local="131352702720000000" remote="131352666720000000" Dst="2" />
<file name="dataTables.bootstrap.min.css" server="C:/wamp64/www/emobi/" local="131352702720000000" remote="131352666720000000" Dst="2" />
<file name="dataTables.foundation.css" server="C:/wamp64/www/emobi/" local="131835891331901985" remote="131835855330000000" Dst="2" />
<file name="dataTables.foundation.min.css" server="C:/wamp64/www/emobi/" local="131835891332051587" remote="131835855330000000" Dst="2" />
<file name="dataTables.jqueryui.css" server="C:/wamp64/www/emobi/" local="131352702720000000" remote="131352666720000000" Dst="2" />
<file name="dataTables.jqueryui.min.css" server="C:/wamp64/www/emobi/" local="131352702720000000" remote="131352666720000000" Dst="2" />
<file name="jquery.dataTables.css" server="C:/wamp64/www/emobi/" local="131835891332241075" remote="131835855330000000" Dst="2" />
<file name="jquery.dataTables.min.css" server="C:/wamp64/www/emobi/" local="131835891332411734" remote="131835855330000000" Dst="2" />
<file name="jquery.dataTables_themeroller.css" server="C:/wamp64/www/emobi/" local="131352702720000000" remote="131352666720000000" Dst="2" />
</dwsync>